hxy_ee165/lab2/result_v4/design.sv
module fifo #(parameter type DATA_TYPE=logic[1:0], parameter N_ADDR_BITS=2)
	(input logic reset, rd_en, wr_en, clk,
	 input DATA_TYPE wr_data,
	 output logic empty, full,
	 output DATA_TYPE rd_data);
    parameter FIFO_DEPTH = 1 << N_ADDR_BITS;
    DATA_TYPE fifo_mem[FIFO_DEPTH-1:0];	
    logic [N_ADDR_BITS:0] rd_ptr, wr_ptr;
    parameter max_f = (1 << (N_ADDR_BITS+1))-1;
    parameter min_f = 0 << N_ADDR_BITS;
    always_ff @(posedge clk)
    begin
	  if (reset)
      begin
        rd_ptr <= min_f;
        wr_ptr <= min_f;
      end
      if (wr_en && !full && !reset)
      begin
        fifo_mem[wr_ptr[N_ADDR_BITS-1:0]] <= wr_data;
        if (wr_ptr < max_f)
        begin
          wr_ptr <= wr_ptr + 1;
        end
        else if (wr_ptr == max_f)
        begin
          wr_ptr <= min_f;
        end
      end
      if (rd_en && !empty && !reset) 
      begin
        if (rd_ptr < max_f)
        begin
          rd_ptr <= rd_ptr + 1;
        end
        else if (rd_ptr == max_f)
        begin
          rd_ptr <= min_f;
        end
      end
    end
    always_comb
    begin
      if (!empty) rd_data = fifo_mem[rd_ptr[N_ADDR_BITS-1:0]];
      empty = (rd_ptr[N_ADDR_BITS:0] == wr_ptr[N_ADDR_BITS:0]);
      full = (rd_ptr[N_ADDR_BITS-1:0] == wr_ptr[N_ADDR_BITS-1:0]) && (rd_ptr[N_ADDR_BITS] != wr_ptr[N_ADDR_BITS]);     
    end
endmodule

hxy_ee165/lab2/result_v4/testbench.sv
module tn_fifo ();
  parameter N_ADDR_BITS=2, FIFO_WIDTH=2;
  logic reset, rd_en, wr_en, clk, fifo_empty, fifo_full;
  logic[FIFO_WIDTH-1:0] wr_data, fifo_rd_data;
  
  //reference module
  parameter n_flops = 1 << N_ADDR_BITS;
  logic [FIFO_WIDTH-1:0] flops [n_flops-1:0], rm_rd_data;
  logic full, empty;
  //logic [3:0] count;
  int n_items;
  //int n_max=2**N_ADDR_BITS;

  fifo F (
    .reset(reset),
    .rd_en(rd_en),
    .wr_en(wr_en),
    .clk(clk),
    .empty(fifo_empty),
    .full(fifo_full),
    .rd_data(fifo_rd_data),
    .wr_data(wr_data)
  );
  
  //reference
  always_ff @(posedge clk)
  begin
    if (reset)
    begin
      n_items = 0;
    end
    /*
    if (wr_en && rd_en && !full && !empty) begin
      flops[0] <= wr_data;
      flops[1] <= flops[0];
      flops[2] <= flops[1];
      flops[3] <= flops[2];
    end
    else begin
      */
    if (wr_en && !full && !reset)
    begin
      flops[0] <= wr_data;
      flops[1] <= flops[0];
      flops[2] <= flops[1];
      flops[3] <= flops[2];
    end
    if (!full && !empty && wr_en && rd_en && !reset)
    begin
    end
    else if (wr_en && !full && !reset)
      n_items <= n_items + 1;
    else if (rd_en && !empty && !reset)
    begin
      n_items <= n_items - 1;
    end
    /*
    end
  */
  end
  
  always_comb
  begin
    if(!empty && n_items > 0) rm_rd_data = flops[n_items-1];
    else if (rd_en && wr_en && n_items == 0)
      rm_rd_data = flops[0];
    else if (!full && !empty && wr_en && rd_en)
      rm_rd_data = flops[n_items];
    if (n_items == 0) begin
      empty = 1;
    end
    else begin
      empty = 0;
    end
    if (n_items == n_flops) begin
      full = 1;
    end
    else begin
      full = 0;
    end
  end
  
  initial
  begin
    $dumpfile("dump.vcd");
    $dumpvars();
  end
  
  initial forever #10 clk = ~clk;
  
  function logic[FIFO_WIDTH-1:0] get_data();
    return $random;
  endfunction: get_data
  
  initial
  begin
    clk = 0;
    reset = 1;
    rd_en = 0;
    wr_en = 0;
    @(negedge clk);
    //@(negedge clk);
    reset = 0;
    
    wr_en = 1;
    rd_en = 1;
    repeat (5)
    begin
      wr_data=get_data();
      @(negedge clk);
    end
    wr_en = 0;
    rd_en = 1;
    repeat (2)
    begin
      //wr_data=get_data();
      @(negedge clk);
    end
    wr_en = 1;
    rd_en = 0;
    repeat (5)
    begin
      wr_data=get_data();
      @(negedge clk);
    end
    wr_en = 1;
    rd_en = 1;
    repeat (2)
    begin
      wr_data=get_data();
      @(negedge clk);
    end
    wr_en = 0;
    rd_en = 1;
    repeat (3)
    begin
      //wr_data=get_data();
      @(negedge clk);
    end
    
  $stop;
  end
  scoreboard_checker: assert property (
    @(negedge clk) rm_rd_data===fifo_rd_data
  ) //$display("T=%0t: correct", $time);
    else $strobe ("T=%0t: SB=%0x, DUT=%0x", $time, rm_rd_data, fifo_rd_data);
  scoreboard_checker1: assert property (
    @(negedge clk) disable iff (reset)(full===fifo_full)
  ) //$display("T=%0t: correct full/empty", $time);
    else $strobe ("T=%0t: SB_full=%0u, DUT_full=%0u", $time, full, fifo_full);
  scoreboard_checker2: assert property (
    @(negedge clk) disable iff (reset)(empty===fifo_empty)
  ) //$display("T=%0t: correct full/empty", $time);
    else $strobe ("T=%0t: SB_empty=%0u, DUT_empty=%0u", $time, empty, fifo_empty);
endmodule

hxy_ee165/lab2/result_v4/dump.vcd
$date
	Thu Mar  4 22:32:54 2021
$end
$version
	QuestaSim Version 2020.1_1
$end
$timescale
	1ns
$end

$scope module tn_fifo $end
$var parameter 32 ! N_ADDR_BITS $end
$var parameter 32 " FIFO_WIDTH $end
$var parameter 32 # n_flops $end
$var reg 1 $ reset $end
$var reg 1 % rd_en $end
$var reg 1 & wr_en $end
$var reg 1 ' clk $end
$var reg 1 ( fifo_empty $end
$var reg 1 ) fifo_full $end
$var reg 2 * wr_data [1:0] $end
$var reg 2 + fifo_rd_data [1:0] $end
$var reg 2 , rm_rd_data [1:0] $end
$var reg 1 - full $end
$var reg 1 . empty $end
$var integer 32 / n_items $end

$scope function get_data $end
$var reg 2 0 get_data [1:0] $end
$upscope $end

$scope begin scoreboard_checker $end
$upscope $end

$scope begin scoreboard_checker1 $end
$upscope $end

$scope begin scoreboard_checker2 $end
$upscope $end

$scope module F $end
$var parameter 32 1 N_ADDR_BITS $end
$var parameter 32 2 FIFO_DEPTH $end
$var parameter 32 3 max_f $end
$var parameter 32 4 min_f $end
$var wire 1 5 reset $end
$var wire 1 6 rd_en $end
$var wire 1 7 wr_en $end
$var wire 1 8 clk $end
$var reg 2 9 wr_data [1:0] $end
$var reg 1 : empty $end
$var reg 1 ; full $end
$var reg 2 < rd_data [1:0] $end
$var reg 3 = rd_ptr [2:0] $end
$var reg 3 > wr_ptr [2:0] $end
$upscope $end
$upscope $end

$scope begin std $end
$upscope $end
$enddefinitions $end
#0
$dumpvars
1$
0%
0&
0'
x(
x)
bx *
bx +
bx ,
0-
1.
bx 9
x:
x;
bx <
bx =
bx >
bx 0
b10 !
b10 "
b100 #
b10 1
b100 2
b111 3
b0 4
b0 /
08
07
06
15
$end
#10
1'
18
b0 =
b0 >
1:
0;
0)
1(
#20
0'
08
0$
1&
1%
b0 0
b0 *
b0 9
05
17
16
#30
1'
18
b1 >
b1 /
0.
0:
0(
#40
0'
08
b1 0
b1 *
b1 9
#50
1'
18
b10 >
b1 =
b1 ,
b1 <
b1 +
#60
0'
08
#70
1'
18
b11 >
b10 =
#80
0'
08
b11 0
b11 *
b11 9
#90
1'
18
b100 >
b11 =
b11 ,
b11 <
b11 +
#100
0'
08
b1 0
b1 *
b1 9
#110
1'
18
b101 >
b100 =
b1 ,
b1 <
b1 +
#120
0'
08
0&
07
#130
1'
18
b101 =
b0 /
1.
1:
1(
#140
0'
08
#150
1'
18
#160
0'
08
1&
0%
17
06
#170
1'
18
b110 >
b1 /
0.
0:
0(
#180
0'
08
#190
1'
18
b111 >
b10 /
#200
0'
08
b10 0
b10 *
b10 9
#210
1'
18
b0 >
b11 /
#220
0'
08
b1 0
b1 *
b1 9
#230
1'
18
b1 >
b100 /
1-
1;
1)
#240
0'
08
#250
1'
18
#260
0'
08
1%
b10 0
b10 *
b10 9
16
#270
1'
18
b110 =
b11 /
0-
0;
0)
#280
0'
08
b1 0
b1 *
b1 9
#290
1'
18
b10 >
b111 =
b10 ,
b10 <
b10 +
#300
0'
08
0&
07
#310
1'
18
b0 =
b10 /
b1 ,
b1 <
b1 +
#320
0'
08
#330
1'
18
b1 =
b1 /
#340
0'
08
#350
1'
18
b10 =
b0 /
1.
1:
1(
