hxy_ee165/lab2/design.sv
module fifo #(parameter type DATA_TYPE=logic[1:0], parameter N_ADDR_BITS=2)
	(input logic reset, rd_en, wr_en, clk,
	 input DATA_TYPE wr_data,
	 output logic empty, full,
	 output DATA_TYPE rd_data);
    parameter FIFO_DEPTH = 1 << N_ADDR_BITS;
    DATA_TYPE fifo_mem[FIFO_DEPTH-1:0];	
    logic [N_ADDR_BITS:0] rd_ptr, wr_ptr;

    always_ff @(posedge clk)
    begin
	  if (reset)
      begin
        rd_ptr <= 0;
        wr_ptr <= 0;
        fifo_mem[0] <= 2'b00;
        fifo_mem[1] <= 2'b00;
        fifo_mem[2] <= 2'b00;
        fifo_mem[3] <= 2'b00;
      end
      else if (wr_en && !full)
      begin
        fifo_mem[wr_ptr[1:0]] <= wr_data;
        if (wr_ptr < 3'b111)
        begin
          wr_ptr <= wr_ptr + 1;
        end
        else if (wr_ptr == 3'b111)
        begin
          wr_ptr <= 3'b000;
        end
      end
      else if (rd_en && !empty) 
      begin
        if (rd_ptr < 3'b111)
        begin
          rd_ptr <= rd_ptr + 1;
        end
        else if (rd_ptr == 3'b111)
        begin
          rd_ptr <= 3'b000;
        end
      end
    end
    always_comb
    begin
      if (!empty) rd_data <= fifo_mem[rd_ptr[1:0]];
      empty = (rd_ptr[2:0] == wr_ptr[2:0]);
      full = (rd_ptr[1:0] == wr_ptr[1:0]) && (rd_ptr[2] != wr_ptr[2]);     
    end
endmodule

hxy_ee165/lab2/result_v1/testbench.sv
module tn_fifo ();
  parameter N_ADDR_BITS=2, FIFO_WIDTH=2;
  logic reset, rd_en, wr_en, clk, fifo_empty, fifo_full;
  logic[FIFO_WIDTH-1:0] wr_data, rd_data;
  
  //reference module
  parameter n_flops = 1 << N_ADDR_BITS;
  logic [FIFO_WIDTH-1:0] flops [n_flops-1:0], rm_rd_data;
  logic [3:0] count;
  int n_items;

  
  fifo F (
    .reset(reset),
    .rd_en(rd_en),
    .wr_en(wr_en),
    .clk(clk),
    .empty(fifo_empty),
    .full(fifo_full),
    .rd_data(rd_data),
    .wr_data(wr_data)
  );
  
  //reference
  always_ff @(posedge clk)
  begin
    if (reset)
    begin
      flops[0] <= 2'b00;
      flops[1] <= 2'b00;
      flops[2] <= 2'b00;
      flops[3] <= 2'b00;
      count = 4'b0000;
    end
    else if (wr_en)
    begin
      flops[0] <= wr_data;
      flops[1] <= flops[0];
      flops[2] <= flops[1];
      flops[3] <= flops[2];
      count <= count + 1;
    end
    else if (rd_en)
    begin
      count <= count - 1;
    end
  end
  
  always_comb
  begin
    rm_rd_data = flops[count];
  end
  
  initial
  begin
    $dumpfile("dump.vcd");
    $dumpvars();
  end
  
  initial forever #10 clk = ~clk;
  
  function logic[FIFO_WIDTH-1:0] get_data();
    return $random;
  endfunction: get_data
  
  initial
  begin
    clk = 0;
    reset = 1;
    rd_en = 0;
    wr_en = 0;
    @(negedge clk);
    @(negedge clk);
    reset = 0;
    
    repeat (6)
    begin
      wr_en = 1;
      repeat (3)
      begin
        wr_data=get_data();
        @(negedge clk);
      end
      wr_en = 0;
      rd_en = 1;
      repeat (2)
      begin
        wr_data=get_data();
        @(negedge clk);
      end
      rd_en = 0;
    end
    $stop;
  end
  
endmodule

hxy_ee165/lab2/result_v1/dump.vcd
$date
	Sun Feb 28 09:09:22 2021
$end
$version
	QuestaSim Version 2020.1_1
$end
$timescale
	1ns
$end

$scope module tn_fifo $end
$var parameter 32 ! N_ADDR_BITS $end
$var parameter 32 " FIFO_WIDTH $end
$var parameter 32 # n_flops $end
$var reg 1 $ reset $end
$var reg 1 % rd_en $end
$var reg 1 & wr_en $end
$var reg 1 ' clk $end
$var reg 1 ( fifo_empty $end
$var reg 1 ) fifo_full $end
$var reg 2 * wr_data [1:0] $end
$var reg 2 + rd_data [1:0] $end
$var reg 2 , rm_rd_data [1:0] $end
$var reg 4 - count [3:0] $end
$var integer 32 . n_items $end

$scope function get_data $end
$var reg 2 / get_data [1:0] $end
$upscope $end

$scope module F $end
$var parameter 32 0 N_ADDR_BITS $end
$var parameter 32 1 FIFO_DEPTH $end
$var wire 1 2 reset $end
$var wire 1 3 rd_en $end
$var wire 1 4 wr_en $end
$var wire 1 5 clk $end
$var reg 2 6 wr_data [1:0] $end
$var reg 1 7 empty $end
$var reg 1 8 full $end
$var reg 2 9 rd_data [1:0] $end
$var reg 3 : rd_ptr [2:0] $end
$var reg 3 ; wr_ptr [2:0] $end
$upscope $end
$upscope $end

$scope begin std $end
$upscope $end
$enddefinitions $end
#0
$dumpvars
1$
0%
0&
0'
x(
x)
bx *
bx +
bx ,
bx -
bx 6
x7
x8
bx 9
bx :
bx ;
bx /
b10 !
b10 "
b100 #
b10 0
b100 1
b0 .
05
04
03
12
$end
#10
1'
15
b0 -
b0 :
b0 ;
b0 ,
17
08
0)
1(
#20
0'
05
#30
1'
15
#40
0'
05
0$
1&
b0 /
b0 *
b0 6
02
14
#50
1'
15
b1 ;
b1 -
07
0(
#60
0'
05
b1 /
b1 *
b1 6
#70
1'
15
b10 ;
b10 -
#80
0'
05
#90
1'
15
b11 ;
b11 -
#100
0'
05
0&
1%
b11 /
b11 *
b11 6
04
13
#110
1'
15
b0 9
b1 :
b10 -
b0 +
#120
0'
05
b1 /
b1 *
b1 6
#130
1'
15
b1 9
b10 :
b1 -
b1 +
b1 ,
#140
0'
05
0%
1&
03
14
#150
1'
15
b100 ;
b10 -
#160
0'
05
#170
1'
15
b101 ;
b11 -
#180
0'
05
b10 /
b10 *
b10 6
#190
1'
15
b110 ;
b100 -
bx ,
18
1)
#200
0'
05
0&
1%
b1 /
b1 *
b1 6
04
13
#210
1'
15
b11 :
b11 -
b1 ,
08
0)
#220
0'
05
#230
1'
15
b100 :
b10 -
#240
0'
05
0%
1&
b10 /
b10 *
b10 6
03
14
#250
1'
15
b111 ;
b11 -
#260
0'
05
b1 /
b1 *
b1 6
#270
1'
15
b0 ;
b100 -
bx ,
18
1)
#280
0'
05
#290
1'
15
b1 ;
b101 -
08
0)
#300
0'
05
0&
1%
b0 /
b0 *
b0 6
04
13
#310
1'
15
bx 9
b101 :
b100 -
bx +
18
1)
#320
0'
05
b1 /
b1 *
b1 6
#330
1'
15
b110 :
b11 -
b10 ,
08
0)
#340
0'
05
0%
1&
b10 /
b10 *
b10 6
03
14
#350
1'
15
b10 ;
b100 -
bx ,
18
1)
#360
0'
05
b1 /
b1 *
b1 6
#370
1'
15
b11 ;
b101 -
08
0)
#380
0'
05
b10 /
b10 *
b10 6
#390
1'
15
b100 ;
b110 -
#400
0'
05
0&
1%
b1 /
b1 *
b1 6
04
13
#410
1'
15
b111 :
b101 -
#420
0'
05
b11 /
b11 *
b11 6
#430
1'
15
b0 :
b100 -
18
1)
#440
0'
05
0%
1&
b10 /
b10 *
b10 6
03
14
#450
1'
15
b101 ;
b101 -
08
0)
#460
0'
05
b11 /
b11 *
b11 6
#470
1'
15
b110 ;
b110 -
#480
0'
05
b10 /
b10 *
b10 6
#490
1'
15
b111 ;
b111 -
#500
0'
05
0&
1%
04
13
#510
1'
15
b1 9
b1 :
b110 -
b1 +
#520
0'
05
b0 /
b0 *
b0 6
#530
1'
15
b10 9
b10 :
b101 -
b10 +
#540
0'
05
0%
1&
b1 /
b1 *
b1 6
03
14
#550
1'
15
b0 ;
b110 -
#560
0'
05
b0 /
b0 *
b0 6
#570
1'
15
b1 ;
b111 -
#580
0'
05
b1 /
b1 *
b1 6
#590
1'
15
b10 ;
b1000 -
17
1(
#600
0'
05
0&
1%
04
13
#610
1'
15
b1 9
b11 :
b111 -
b1 +
07
0(
#620
0'
05
#630
1'
15
b10 9
b100 :
b110 -
b10 +
#640
0'
05
0%
